setup.py
HarvestNet/__init__.py
HarvestNet/ftp.py
HarvestNet/main.py
harvestnet.egg-info/PKG-INFO
harvestnet.egg-info/SOURCES.txt
harvestnet.egg-info/dependency_links.txt
harvestnet.egg-info/top_level.txt