Metadata-Version: 1.2
Name: harvestnet
Version: 1.0
Summary: HarvestNet
Home-page: UNKNOWN
Author: waterlily
Author-email: b1929595403@gmail.com
License: MIT License
Platform: any
Requires-Python: >=3.7.*
